[{"title": "Symphony no. 2, op. 30, \"Romantic\"", "subtitle": "", "searchterms": "", "popular": "0", "recommended": "1", "id": "3594", "genre": "Orchestral"}, {"title": "A Prayer of the Middle Ages, for chorus", "subtitle": "", "searchterms": "", "popular": "0", "recommended": "0", "id": "3565", "genre": "Vocal"}, {"title": "Centennial March", "subtitle": "", "searchterms": "", "popular": "0", "recommended": "0", "id": "3589", "genre": "Orchestral"}, {"title": "Chorale and Alleluia, for chorus and orchestra", "subtitle": "", "searchterms": "", "popular": "0", "recommended": "0", "id": "3551", "genre": "Vocal"}, {"title": "Concerto da camera, for string quartet, op. 7", "subtitle": "", "searchterms": "", "popular": "0", "recommended": "0", "id": "3573", "genre": "Chamber"}, {"title": "Concerto for organ, harp and strings in C major, op.  22/3", "subtitle": "", "searchterms": "", "popular": "0", "recommended": "0", "id": "3586", "genre": "Orchestral"}, {"title": "Concerto for piano and orchestra in G major, op.  36", "subtitle": "", "searchterms": "", "popular": "0", "recommended": "0", "id": "3566", "genre": "Orchestral"}, {"title": "Dies Natalis II, for wind ensemble", "subtitle": "", "searchterms": "", "popular": "0", "recommended": "0", "id": "3564", "genre": "Orchestral"}, {"title": "Dies Natalis no. 1, for orchestra", "subtitle": "", "searchterms": "", "popular": "0", "recommended": "0", "id": "3576", "genre": "Orchestral"}, {"title": "Elegy in Memory of Serge Koussevitsky, op. 44", "subtitle": "", "searchterms": "", "popular": "0", "recommended": "0", "id": "3559", "genre": "Orchestral"}, {"title": "Enchantment, for piano", "subtitle": "", "searchterms": "", "popular": "0", "recommended": "0", "id": "3599", "genre": "Keyboard"}, {"title": "Fantasy Variations on a Theme of Youth, for piano and orchestra, op. 40", "subtitle": "", "searchterms": "", "popular": "0", "recommended": "0", "id": "3577", "genre": "Orchestral"}, {"title": "For the First Time, for piano", "subtitle": "", "searchterms": "", "popular": "0", "recommended": "0", "id": "3560", "genre": "Keyboard"}, {"title": "For the First Time, suite for orchestra", "subtitle": "", "searchterms": "", "popular": "0", "recommended": "0", "id": "3556", "genre": "Orchestral"}, {"title": "Harp Christmas, for wind ensemble", "subtitle": "", "searchterms": "", "popular": "0", "recommended": "0", "id": "3592", "genre": "Orchestral"}, {"title": "How Excellent Thy Name, for chorus and organ, op. 41", "subtitle": "", "searchterms": "", "popular": "0", "recommended": "0", "id": "3574", "genre": "Vocal"}, {"title": "Lament for Beowulf, for chorus and orchestra, op. 25", "subtitle": "", "searchterms": "", "popular": "0", "recommended": "0", "id": "3572", "genre": "Vocal"}, {"title": "Laude, Chorale, Variations, and Metamorphoses, for band", "subtitle": "", "searchterms": "", "popular": "0", "recommended": "0", "id": "3555", "genre": "Orchestral"}, {"title": "Lumen in Christo, for chorus and orchestra", "subtitle": "", "searchterms": "", "popular": "0", "recommended": "0", "id": "3575", "genre": "Vocal"}, {"title": "Lux aeterna, for viola and orchestra, op. 24", "subtitle": "", "searchterms": "", "popular": "0", "recommended": "0", "id": "3581", "genre": "Orchestral"}, {"title": "Merry Mount,, op. 31", "subtitle": "Opera", "searchterms": "", "popular": "0", "recommended": "0", "id": "3571", "genre": "Stage"}, {"title": "Merry Mount, suite from the opera, op. 31", "subtitle": "", "searchterms": "", "popular": "0", "recommended": "0", "id": "3550", "genre": "Stage"}, {"title": "Miniatures  for piano, no. 1, Reminiscence, op. 12, no. 1", "subtitle": "", "searchterms": "", "popular": "0", "recommended": "0", "id": "3585", "genre": "Keyboard"}, {"title": "Miniatures  for piano, no. 2, Lullaby, op. 12, no. 2", "subtitle": "", "searchterms": "", "popular": "0", "recommended": "0", "id": "3552", "genre": "Keyboard"}, {"title": "Miniatures  for piano, No 3, Longing, op. 12, no. 3", "subtitle": "", "searchterms": "", "popular": "0", "recommended": "0", "id": "3563", "genre": "Keyboard"}, {"title": "Mosaics, for orchestra", "subtitle": "", "searchterms": "", "popular": "0", "recommended": "0", "id": "3568", "genre": "Orchestral"}, {"title": "Nymphs and Satyr, ballet", "subtitle": "", "searchterms": "", "popular": "0", "recommended": "0", "id": "3595", "genre": "Stage"}, {"title": "Pan and the Priest, symphonic poem op. 26", "subtitle": "", "searchterms": "", "popular": "0", "recommended": "0", "id": "3557", "genre": "Orchestral"}, {"title": "Pastorale, for oboe and piano, op. 38", "subtitle": "", "searchterms": "", "popular": "0", "recommended": "0", "id": "3570", "genre": "Orchestral"}, {"title": "Poèmes érotiques, for piano, no. 1, \"Peace\", op. 9, no. 1", "subtitle": "", "searchterms": "", "popular": "0", "recommended": "0", "id": "3590", "genre": "Keyboard"}, {"title": "Poèmes érotiques, for piano, no. 2, Joy, op. 9, no. 2", "subtitle": "", "searchterms": "", "popular": "0", "recommended": "0", "id": "3580", "genre": "Keyboard"}, {"title": "Poèmes érotiques, for piano, no. 3, Desire, op. 9, no. 3", "subtitle": "", "searchterms": "", "popular": "0", "recommended": "0", "id": "3588", "genre": "Keyboard"}, {"title": "Rhythmic Variations on 2 Ancient Hymns, for orchestra", "subtitle": "", "searchterms": "", "popular": "0", "recommended": "0", "id": "3567", "genre": "Orchestral"}, {"title": "Serenade for flute, harp and strings, op. 35", "subtitle": "", "searchterms": "", "popular": "0", "recommended": "0", "id": "3582", "genre": "Orchestral"}, {"title": "Slumber Song, for piano", "subtitle": "", "searchterms": "", "popular": "0", "recommended": "0", "id": "3593", "genre": "Keyboard"}, {"title": "Song of Democracy, for chorus and orchestra, op.  44", "subtitle": "", "searchterms": "", "popular": "0", "recommended": "0", "id": "3596", "genre": "Vocal"}, {"title": "String Quartet, op. 23", "subtitle": "", "searchterms": "", "popular": "0", "recommended": "0", "id": "3598", "genre": "Chamber"}, {"title": "Summer Seascape no. 2, for viola and strings", "subtitle": "", "searchterms": "", "popular": "0", "recommended": "0", "id": "3587", "genre": "Chamber"}, {"title": "Symphony no. 1 in E minor, op. 22, \"Nordic\"", "subtitle": "", "searchterms": "", "popular": "0", "recommended": "0", "id": "3562", "genre": "Orchestral"}, {"title": "Symphony no. 3, op. 33", "subtitle": "", "searchterms": "", "popular": "0", "recommended": "0", "id": "3554", "genre": "Orchestral"}, {"title": "Symphony no. 4, op. 34, \"The Requiem\"", "subtitle": "", "searchterms": "", "popular": "0", "recommended": "0", "id": "3591", "genre": "Orchestral"}, {"title": "Symphony no. 6", "subtitle": "", "searchterms": "", "popular": "0", "recommended": "0", "id": "3584", "genre": "Orchestral"}, {"title": "Symphony no. 7, \"A Sea Symphony\"", "subtitle": "", "searchterms": "", "popular": "0", "recommended": "0", "id": "3597", "genre": "Orchestral"}, {"title": "The Cherubic Hymn, for chorus, op. 37", "subtitle": "", "searchterms": "", "popular": "0", "recommended": "0", "id": "3553", "genre": "Vocal"}, {"title": "Études  for piano, no. 1, Studio ritmico, op. 18, no. 1", "subtitle": "", "searchterms": "", "popular": "0", "recommended": "0", "id": "3569", "genre": "Keyboard"}, {"title": "Études  for piano, no. 2, Studio melodico, op. 18, no. 2", "subtitle": "", "searchterms": "", "popular": "0", "recommended": "0", "id": "3583", "genre": "Keyboard"}, {"title": "Études  for piano, no. 3, Poema Idillico, op. 18, no. 3", "subtitle": "", "searchterms": "", "popular": "0", "recommended": "0", "id": "3561", "genre": "Keyboard"}]